<?xml version="1.0" encoding="utf-8"?>
<OPCUAObject xmlns:xsi="http://www.w3.org/2001/XMLSchema-instance" xmlns:xsd="http://www.w3.org/2001/XMLSchema">
  <OPCUAVariable UID="B4E2C515C95D8C61" Enabled="false">
    <OPCUAAttribute Name="AccessLevel" Value="1" Locked="true" AttributeMask="CurrentRead;True" />
    <Extensions>
      <Extension>
        <RTAddress>V1;${VariableFullPath}</RTAddress>
      </Extension>
    </Extensions>
  </OPCUAVariable>
  <OPCUAVariable UID="476FFD2DF2FDC0EF" Enabled="false">
    <OPCUAAttribute Name="Exposed" Value="True" Locked="false" AttributeMask="True;True|False;True" />
    <Extensions>
      <Extension>
        <RTAddress>V1;${VariableFullPath};Trigger=CNF</RTAddress>
      </Extension>
    </Extensions>
  </OPCUAVariable>
</OPCUAObject>